heco/__init__.py
heco/dialects/__init__.py
heco/dialects/fhe.py
heco/frontend/__init__.py
heco/frontend/dialects/__init__.py
heco/frontend/dialects/fhe.py
heco-0.0.2.dist-info/LICENSE
heco-0.0.2.dist-info/METADATA
heco-0.0.2.dist-info/WHEEL
heco-0.0.2.dist-info/top_level.txt
heco-0.0.2.dist-info/RECORD
