Metadata-Version: 2.1
Name: heco
Version: 0.0.2
Summary: HECO is an optimizing compiler for Fully Homomorphic Encryption (FHE).
Author-email: Alex Viand <alexander.viand@inf.ethz.ch>
License: MIT License        
Project-URL: Homepage, https://github.com/MarbleHE/HECO
Project-URL: Bug Tracker, https://github.com/MarbleHE/HECO/issues
Classifier: Programming Language :: Python :: 3
Classifier: License :: OSI Approved :: MIT License
Classifier: Operating System :: OS Independent
Requires-Python: >=3.10
License-File: LICENSE
Requires-Dist: frozenlist
